{
   "data": {
      "array": [
         {
            "carId": 1008463,
            "carName": "D 60",
            "carType": "O",
            "firstCountry": "FR"
         },
         {
            "carId": 1008466,
            "carName": "D 60",
            "carType": "O",
            "firstCountry": "FR"
         },
         {
            "carId": 1022247,
            "carName": "D 60.160",
            "carType": "O",
            "firstCountry": "FR"
         },
         {
            "carId": 1022248,
            "carName": "D 60.185",
            "carType": "O",
            "firstCountry": "FR"
         },
         {
            "carId": 1022255,
            "carName": "D 65.160",
            "carType": "O",
            "firstCountry": "FR"
         },
         {
            "carId": 1022256,
            "carName": "D 65.185",
            "carType": "O",
            "firstCountry": "FR"
         },
         {
            "carId": 1022257,
            "carName": "D 70.160",
            "carType": "O",
            "firstCountry": "FR"
         },
         {
            "carId": 1022258,
            "carName": "D 70.185",
            "carType": "O",
            "firstCountry": "FR"
         },
         {
            "carId": 1008464,
            "carName": "D 75",
            "carType": "O",
            "firstCountry": "FR"
         },
         {
            "carId": 1022259,
            "carName": "D 75.62",
            "carType": "O",
            "firstCountry": "FR"
         },
         {
            "carId": 1014750,
            "carName": "D 75.160",
            "carType": "O",
            "firstCountry": "FR"
         },
         {
            "carId": 1014751,
            "carName": "D 75.185",
            "carType": "O",
            "firstCountry": "FR"
         },
         {
            "carId": 1014752,
            "carName": "D 75.207",
            "carType": "O",
            "firstCountry": "FR"
         },
         {
            "carId": 1008469,
            "carName": "D 75 T",
            "carType": "O",
            "firstCountry": "FR"
         },
         {
            "carId": 1008467,
            "carName": "D 75",
            "carType": "O",
            "firstCountry": "FR"
         },
         {
            "carId": 1008470,
            "carName": "D 75 T",
            "carType": "O",
            "firstCountry": "FR"
         },
         {
            "carId": 1022249,
            "carName": "D 80.160",
            "carType": "O",
            "firstCountry": "FR"
         },
         {
            "carId": 1022250,
            "carName": "D 80.185",
            "carType": "O",
            "firstCountry": "FR"
         },
         {
            "carId": 1022260,
            "carName": "D 85.160",
            "carType": "O",
            "firstCountry": "FR"
         },
         {
            "carId": 1022261,
            "carName": "D 85.185",
            "carType": "O",
            "firstCountry": "FR"
         },
         {
            "carId": 1008465,
            "carName": "D 90",
            "carType": "O",
            "firstCountry": "FR"
         },
         {
            "carId": 1014753,
            "carName": "D 90.160",
            "carType": "O",
            "firstCountry": "FR"
         },
         {
            "carId": 1008468,
            "carName": "D 90",
            "carType": "O",
            "firstCountry": "FR"
         },
         {
            "carId": 1014754,
            "carName": "D 90.185",
            "carType": "O",
            "firstCountry": "FR"
         },
         {
            "carId": 1014755,
            "carName": "D 90.207",
            "carType": "O",
            "firstCountry": "FR"
         },
         {
            "carId": 1008471,
            "carName": "D 100",
            "carType": "O",
            "firstCountry": "FR"
         },
         {
            "carId": 1022251,
            "carName": "D 100.160",
            "carType": "O",
            "firstCountry": "FR"
         },
         {
            "carId": 1008472,
            "carName": "D 100",
            "carType": "O",
            "firstCountry": "FR"
         },
         {
            "carId": 1022252,
            "carName": "D 100.185",
            "carType": "O",
            "firstCountry": "FR"
         },
         {
            "carId": 1022253,
            "carName": "D 110.160",
            "carType": "O",
            "firstCountry": "FR"
         },
         {
            "carId": 1022254,
            "carName": "D 110.185",
            "carType": "O",
            "firstCountry": "FR"
         },
         {
            "carId": 1008473,
            "carName": "D 120",
            "carType": "O",
            "firstCountry": "FR"
         },
         {
            "carId": 1014756,
            "carName": "D 120.160",
            "carType": "O",
            "firstCountry": "FR"
         },
         {
            "carId": 1008474,
            "carName": "D 120",
            "carType": "O",
            "firstCountry": "FR"
         },
         {
            "carId": 1014757,
            "carName": "D 120.185",
            "carType": "O",
            "firstCountry": "FR"
         },
         {
            "carId": 1014758,
            "carName": "D 120.207",
            "carType": "O",
            "firstCountry": "FR"
         },
         {
            "carId": 1022262,
            "carName": "D 120.160",
            "carType": "O",
            "firstCountry": "FR"
         },
         {
            "carId": 1014759,
            "carName": "D 120.185",
            "carType": "O",
            "firstCountry": "FR"
         },
         {
            "carId": 1014760,
            "carName": "D 120.207",
            "carType": "O",
            "firstCountry": "FR"
         }
      ]
   },
   "status": 200
}