{
   "data": {
      "array": [
         {
            "articleId": 626825603,
            "articleLinkId": 626825606,
            "articleNo": "2111115",
            "articleStateId": 8,
            "brandName": "VALEO",
            "brandNo": 21,
            "genericArticleId": 234,
            "genericArticleName": "Cylindre émetteur, embrayage",
            "sortNo": 626825606
         },
         {
            "articleId": 626825922,
            "articleLinkId": 626825924,
            "articleNo": "2111615",
            "articleStateId": 8,
            "brandName": "VALEO",
            "brandNo": 21,
            "genericArticleId": 234,
            "genericArticleName": "Cylindre émetteur, embrayage",
            "sortNo": 626825924
         },
         {
            "articleId": 446543343,
            "articleLinkId": 446543344,
            "articleNo": "874307",
            "articleStateId": 1,
            "brandName": "VALEO",
            "brandNo": 21,
            "genericArticleId": 234,
            "genericArticleName": "Cylindre émetteur, embrayage",
            "sortNo": 446543344
         },
         {
            "articleId": 446543759,
            "articleLinkId": 446543791,
            "articleNo": "874310",
            "articleStateId": 1,
            "brandName": "VALEO",
            "brandNo": 21,
            "genericArticleId": 234,
            "genericArticleName": "Cylindre émetteur, embrayage",
            "sortNo": 446543791
         }
      ]
   },
   "status": 200
}