{
   "data": {
      "array": [
         {
            "articleId": 14257137,
            "articleLinkId": 14257233,
            "articleNo": "826330",
            "articleStateId": 8,
            "brandName": "VALEO",
            "brandNo": 21,
            "genericArticleId": 479,
            "genericArticleName": "Kit d'embrayage",
            "sortNo": 14257233
         },
         {
            "articleId": 159907673,
            "articleLinkId": 1225905437,
            "articleNo": "834179",
            "articleStateId": 8,
            "brandName": "VALEO",
            "brandNo": 21,
            "genericArticleId": 479,
            "genericArticleName": "Kit d'embrayage",
            "sortNo": 1225905437
         }
      ]
   },
   "status": 200
}