{
   "data": {
      "array": [
         {
            "articleId": 14225016,
            "articleLinkId": 14226508,
            "articleNo": "819749",
            "articleStateId": 1,
            "brandName": "VALEO",
            "brandNo": 21,
            "genericArticleId": 1103,
            "genericArticleName": "Interrupteur de température, ventilateur de radiateur",
            "sortNo": 14226508
         },
         {
            "articleId": 14227663,
            "articleLinkId": 14228148,
            "articleNo": "819781",
            "articleStateId": 1,
            "brandName": "VALEO",
            "brandNo": 21,
            "genericArticleId": 1103,
            "genericArticleName": "Interrupteur de température, ventilateur de radiateur",
            "sortNo": 14228148
         },
         {
            "articleId": 14236617,
            "articleLinkId": 14236867,
            "articleNo": "820033",
            "articleStateId": 9,
            "brandName": "VALEO",
            "brandNo": 21,
            "genericArticleId": 1103,
            "genericArticleName": "Interrupteur de température, ventilateur de radiateur",
            "sortNo": 14236867
         }
      ]
   },
   "status": 200
}