{
   "data": {
      "array": [
         {
            "articleId": 13362666,
            "articleLinkId": 13394163,
            "articleNo": "574117",
            "articleStateId": 1,
            "brandName": "VALEO",
            "brandNo": 21,
            "genericArticleId": 298,
            "genericArticleName": "Balai d'essuie-glace",
            "sortNo": 13394163
         },
         {
            "articleId": 378573079,
            "articleLinkId": 435585396,
            "articleNo": "574125",
            "articleStateId": 1,
            "brandName": "VALEO",
            "brandNo": 21,
            "genericArticleId": 298,
            "genericArticleName": "Balai d'essuie-glace",
            "sortNo": 435585396
         },
         {
            "articleId": 13376089,
            "articleLinkId": 13385284,
            "articleNo": "574150",
            "articleStateId": 1,
            "brandName": "VALEO",
            "brandNo": 21,
            "genericArticleId": 298,
            "genericArticleName": "Balai d'essuie-glace",
            "sortNo": 13385284
         },
         {
            "articleId": 13381486,
            "articleLinkId": 13391442,
            "articleNo": "574158",
            "articleStateId": 1,
            "brandName": "VALEO",
            "brandNo": 21,
            "genericArticleId": 298,
            "genericArticleName": "Balai d'essuie-glace",
            "sortNo": 13391442
         },
         {
            "articleId": 346396314,
            "articleLinkId": 369484765,
            "articleNo": "575006",
            "articleStateId": 1,
            "brandName": "VALEO",
            "brandNo": 21,
            "genericArticleId": 298,
            "genericArticleName": "Balai d'essuie-glace",
            "sortNo": 369484765
         },
         {
            "articleId": 346396316,
            "articleLinkId": 369489419,
            "articleNo": "575008",
            "articleStateId": 1,
            "brandName": "VALEO",
            "brandNo": 21,
            "genericArticleId": 298,
            "genericArticleName": "Balai d'essuie-glace",
            "sortNo": 369489419
         },
         {
            "articleId": 13442019,
            "articleLinkId": 13465434,
            "articleNo": "575553",
            "articleStateId": 1,
            "brandName": "VALEO",
            "brandNo": 21,
            "genericArticleId": 298,
            "genericArticleName": "Balai d'essuie-glace",
            "sortNo": 13465434
         },
         {
            "articleId": 13442490,
            "articleLinkId": 13453958,
            "articleNo": "575560",
            "articleStateId": 1,
            "brandName": "VALEO",
            "brandNo": 21,
            "genericArticleId": 298,
            "genericArticleName": "Balai d'essuie-glace",
            "sortNo": 13453958
         },
         {
            "articleId": 13523069,
            "articleLinkId": 13548280,
            "articleNo": "576089",
            "articleStateId": 9,
            "brandName": "VALEO",
            "brandNo": 21,
            "genericArticleId": 298,
            "genericArticleName": "Balai d'essuie-glace",
            "sortNo": 13548280
         },
         {
            "articleId": 13531226,
            "articleLinkId": 13537645,
            "articleNo": "576093",
            "articleStateId": 9,
            "brandName": "VALEO",
            "brandNo": 21,
            "genericArticleId": 298,
            "genericArticleName": "Balai d'essuie-glace",
            "sortNo": 13537645
         },
         {
            "articleId": 13531750,
            "articleLinkId": 13540666,
            "articleNo": "576094",
            "articleStateId": 9,
            "brandName": "VALEO",
            "brandNo": 21,
            "genericArticleId": 298,
            "genericArticleName": "Balai d'essuie-glace",
            "sortNo": 13540666
         },
         {
            "articleId": 220383652,
            "articleLinkId": 229772684,
            "articleNo": "578574",
            "articleStateId": 1,
            "brandName": "VALEO",
            "brandNo": 21,
            "genericArticleId": 298,
            "genericArticleName": "Balai d'essuie-glace",
            "sortNo": 229772684
         },
         {
            "articleId": 220384348,
            "articleLinkId": 229772255,
            "articleNo": "578579",
            "articleStateId": 1,
            "brandName": "VALEO",
            "brandNo": 21,
            "genericArticleId": 298,
            "genericArticleName": "Balai d'essuie-glace",
            "sortNo": 229772255
         }
      ]
   },
   "status": 200
}