{
   "data": {
      "array": [
         {
            "carId": 1014643,
            "vehicleDetails": {
               "axisConfiguration": "6x6",
               "carId": 1014643,
               "ccmTech": 10850,
               "constructionType": "Camion plate-forme/Châssis",
               "cylinderCapacityCcm": 10850,
               "manuId": 3763,
               "manuName": "URAL",
               "modId": 10482,
               "modelName": "4320",
               "motorType": "Diesel",
               "powerHpFrom": 209,
               "powerHpTo": 211,
               "powerKwFrom": 154,
               "powerKwTo": 155,
               "tonnage": 1368,
               "typeName": "4320",
               "typeNumber": 14643,
               "yearOfConstrFrom": 197701,
               "rmiTypeId": 76375
            }
         }
      ]
   },
   "status": 200
}