{
   "data": {
      "array": [
         {
            "carId": 1018419,
            "vehicleDetails": {
               "axisConfiguration": "4x4",
               "carId": 1018419,
               "ccmTech": 6057,
               "constructionType": "Tracteur",
               "cylinderCapacityCcm": 6057,
               "manuId": 674,
               "manuName": "SAME",
               "modId": 13170,
               "modelName": "AUDAX ST",
               "motorType": "Diesel",
               "powerHpFrom": 222,
               "powerHpTo": 222,
               "powerKwFrom": 163,
               "powerKwTo": 163,
               "tonnage": 825,
               "typeName": "220",
               "typeNumber": 18419,
               "yearOfConstrFrom": 201311
            }
         }
      ]
   },
   "status": 200
}