{
   "data": {
      "array": [
         {
            "carId": 1042095,
            "vehicleDetails": {
               "axisConfiguration": "6x2/4",
               "carId": 1042095,
               "ccmTech": 12419,
               "constructionType": "Camion plate-forme/Châssis",
               "cylinderCapacityCcm": 12419,
               "manuId": 69,
               "manuName": "MAN",
               "modId": 42090,
               "modelName": "TGX II",
               "motorType": "Diesel",
               "powerHpFrom": 430,
               "powerHpTo": 430,
               "powerKwFrom": 316,
               "powerKwTo": 316,
               "tonnage": 2600,
               "typeName": "26.430",
               "typeNumber": 42095,
               "yearOfConstrFrom": 202002,
               "rmiTypeId": 185240
            }
         }
      ]
   },
   "status": 200
}