{
   "data": {
      "array": [
         {
            "carId": 10528,
            "vehicleDetails": {
               "carId": 10528,
               "ccmTech": 1598,
               "constructionType": "Monospace",
               "cylinder": 4,
               "cylinderCapacityCcm": 1598,
               "cylinderCapacityLiter": 160,
               "fuelType": "Diesel",
               "fuelTypeProcess": "Injection directe",
               "impulsionType": "Traction avant",
               "manuId": 93,
               "manuName": "RENAULT",
               "modId": 8148,
               "modelName": "GRAND SCÉNIC III (JZ0/1_)",
               "motorType": "Diesel",
               "powerHpFrom": 130,
               "powerHpTo": 130,
               "powerKwFrom": 96,
               "powerKwTo": 96,
               "typeName": "1.6 dCi (JZ00, JZ12)",
               "typeNumber": 10528,
               "valves": 4,
               "yearOfConstrFrom": 201104,
               "rmiTypeId": 66766
            },
            "vehicleDocId": "DR10528"
         }
      ]
   },
   "status": 200
}