{
   "data": {
      "array": [
         {
            "carId": 105251,
            "vehicleDetails": {
               "carId": 105251,
               "ccmTech": 749,
               "constructionType": "Moto",
               "cylinder": 2,
               "cylinderCapacityCcm": 749,
               "cylinderCapacityLiter": 75,
               "fuelType": "Essence",
               "fuelTypeProcess": "Injection dans le collecteur d'admission/Carburateur",
               "impulsionType": "Chaîne",
               "manuId": 45,
               "manuName": "HONDA",
               "modId": 12308,
               "modelName": "VT",
               "motorType": "Essence",
               "powerHpFrom": 63,
               "powerHpTo": 63,
               "powerKwFrom": 46,
               "powerKwTo": 46,
               "typeName": "VT 750 C Shadow (RC29)",
               "typeNumber": 105251,
               "valves": 3,
               "yearOfConstrFrom": 198801
            }
         }
      ]
   },
   "status": 200
}