{
   "data": {
      "array": [
         {
            "carId": 117229,
            "vehicleDetails": {
               "carId": 117229,
               "ccmTech": 1995,
               "constructionType": "SUV",
               "cylinder": 4,
               "cylinderCapacityCcm": 1995,
               "cylinderCapacityLiter": 200,
               "fuelType": "Diesel",
               "fuelTypeProcess": "Injection directe",
               "impulsionType": "Traction avant",
               "manuId": 183,
               "manuName": "HYUNDAI",
               "modId": 10515,
               "modelName": "SANTA FÉ III (DM, DMA)",
               "motorType": "Diesel",
               "powerHpFrom": 185,
               "powerHpTo": 185,
               "powerKwFrom": 136,
               "powerKwTo": 136,
               "typeName": "2.0 CRDi",
               "typeNumber": 117229,
               "valves": 4,
               "yearOfConstrFrom": 201505,
               "rmiTypeId": 123627
            },
            "vehicleDocId": "DR117229"
         }
      ]
   },
   "status": 200
}