{
   "data": {
      "array": [
         {
            "carId": 17864,
            "vehicleDetails": {
               "carId": 17864,
               "ccmTech": 2148,
               "constructionType": "A trois volumes",
               "cylinder": 4,
               "cylinderCapacityCcm": 2148,
               "cylinderCapacityLiter": 220,
               "fuelType": "Diesel",
               "fuelTypeProcess": "Injection directe",
               "impulsionType": "Propulsion",
               "manuId": 74,
               "manuName": "MERCEDES-BENZ",
               "modId": 4640,
               "modelName": "CLASSE C (W203)",
               "motorType": "Diesel",
               "powerHpFrom": 150,
               "powerHpTo": 150,
               "powerKwFrom": 110,
               "powerKwTo": 110,
               "typeName": "C 220 CDI (203.008)",
               "typeNumber": 17864,
               "valves": 4,
               "yearOfConstrFrom": 200304,
               "yearOfConstrTo": 200702,
               "rmiTypeId": 13896
            },
            "vehicleDocId": "DR17864"
         }
      ]
   },
   "status": 200
}