{
   "data": {
      "array": [
         {
            "carId": 27239,
            "vehicleDetails": {
               "carId": 27239,
               "ccmTech": 2771,
               "constructionType": "Break",
               "cylinder": 6,
               "cylinderCapacityCcm": 2771,
               "cylinderCapacityLiter": 280,
               "fuelType": "Essence",
               "fuelTypeProcess": "Injection dans le collecteur d'admission/Carburateur",
               "impulsionType": "Traction intégrale",
               "manuId": 5,
               "manuName": "AUDI",
               "modId": 3485,
               "modelName": "A4 B5 Avant (8D5)",
               "motorType": "Essence",
               "powerHpFrom": 190,
               "powerHpTo": 190,
               "powerKwFrom": 140,
               "powerKwTo": 140,
               "typeName": "2.8 quattro",
               "typeNumber": 27239,
               "valves": 5,
               "yearOfConstrFrom": 199903,
               "yearOfConstrTo": 200009,
               "rmiTypeId": 81880
            },
            "vehicleDocId": "DR27239"
         }
      ]
   },
   "status": 200
}