{
   "data": {
      "array": [
         {
            "carId": 3751,
            "vehicleDetails": {
               "brakeSystem": "hydraulique",
               "carId": 3751,
               "ccmTech": 1905,
               "constructionType": "A trois volumes",
               "cylinder": 4,
               "cylinderCapacityCcm": 1905,
               "cylinderCapacityLiter": 190,
               "fuelType": "Diesel",
               "fuelTypeProcess": "Moteur à injection indirecte",
               "impulsionType": "Traction avant",
               "manuId": 88,
               "manuName": "PEUGEOT",
               "modId": 273,
               "modelName": "306 (7B, N3, N5)",
               "motorType": "Diesel",
               "powerHpFrom": 68,
               "powerHpTo": 68,
               "powerKwFrom": 50,
               "powerKwTo": 50,
               "typeName": "1.9 SLD",
               "typeNumber": 3751,
               "valves": 2,
               "yearOfConstrFrom": 199406,
               "yearOfConstrTo": 200105,
               "rmiTypeId": 3444
            },
            "vehicleDocId": "DR3751"
         }
      ]
   },
   "status": 200
}