{
   "data": {
      "array": [
         {
            "carId": 58881,
            "vehicleDetails": {
               "carId": 58881,
               "ccmTech": 1598,
               "constructionType": "Coupé",
               "cylinder": 4,
               "cylinderCapacityCcm": 1598,
               "cylinderCapacityLiter": 160,
               "fuelType": "Diesel",
               "fuelTypeProcess": "Injection directe",
               "impulsionType": "Traction intégrale",
               "manuId": 1523,
               "manuName": "MINI",
               "modId": 11216,
               "modelName": "MINI PACEMAN (R61)",
               "motorType": "Diesel",
               "powerHpFrom": 112,
               "powerHpTo": 112,
               "powerKwFrom": 82,
               "powerKwTo": 82,
               "typeName": "Cooper D ALL4",
               "typeNumber": 58881,
               "valves": 4,
               "yearOfConstrFrom": 201204,
               "yearOfConstrTo": 201609,
               "rmiTypeId": 75943
            },
            "vehicleDocId": "DR58881"
         }
      ]
   },
   "status": 200
}