{
   "data": {
      "array": [
         {
            "carId": 1003346,
            "vehicleDetails": {
               "axisConfiguration": "6x4",
               "carId": 1003346,
               "ccmTech": 13798,
               "constructionType": "Camion basculant",
               "cylinderCapacityCcm": 13798,
               "manuId": 55,
               "manuName": "IVECO",
               "modId": 3870,
               "modelName": "P/PA",
               "motorType": "Diesel",
               "powerHpFrom": 360,
               "powerHpTo": 360,
               "powerKwFrom": 265,
               "powerKwTo": 265,
               "tonnage": 2400,
               "typeName": "330-36 H",
               "typeNumber": 3346,
               "yearOfConstrFrom": 198901,
               "yearOfConstrTo": 199012,
               "rmiTypeId": 19040
            }
         }
      ]
   },
   "status": 200
}