{
   "data": {
      "array": [
         {
            "carId": 1056428,
            "vehicleDetails": {
               "axisConfiguration": "6x2",
               "carId": 1056428,
               "ccmTech": 11967,
               "constructionType": "Camion plate-forme/Châssis",
               "cylinderCapacityCcm": 11967,
               "manuId": 69,
               "manuName": "MAN",
               "modId": 3898,
               "modelName": "F90 Unterflur",
               "motorType": "Diesel",
               "powerHpFrom": 330,
               "powerHpTo": 330,
               "powerKwFrom": 243,
               "powerKwTo": 243,
               "tonnage": 2500,
               "typeName": "25.332 U",
               "typeNumber": 56428,
               "yearOfConstrFrom": 198602,
               "yearOfConstrTo": 199501,
               "rmiTypeId": 209024
            }
         }
      ]
   },
   "status": 200
}