{
   "data": {
      "array": [
         {
            "carId": 1057578,
            "vehicleDetails": {
               "axisConfiguration": "6x2",
               "carId": 1057578,
               "ccmTech": 10837,
               "constructionType": "Tracteur de semi-remorque",
               "cylinderCapacityCcm": 10837,
               "manuId": 24,
               "manuName": "DAF",
               "modId": 43953,
               "modelName": "XD",
               "motorType": "Diesel",
               "powerHpFrom": 367,
               "powerHpTo": 367,
               "powerKwFrom": 270,
               "powerKwTo": 270,
               "tonnage": 2700,
               "typeName": "FTR 370",
               "typeNumber": 57578,
               "yearOfConstrFrom": 202209,
               "rmiTypeId": 211506
            }
         }
      ]
   },
   "status": 200
}