{
   "data": {
      "array": [
         {
            "carId": 130752,
            "vehicleDetails": {
               "carId": 130752,
               "ccmTech": 1199,
               "constructionType": "Monospace",
               "cylinder": 3,
               "cylinderCapacityCcm": 1199,
               "cylinderCapacityLiter": 120,
               "fuelType": "Essence",
               "fuelTypeProcess": "Injection directe",
               "impulsionType": "Traction avant",
               "manuId": 88,
               "manuName": "PEUGEOT",
               "modId": 38589,
               "modelName": "RIFTER",
               "motorType": "Essence",
               "powerHpFrom": 110,
               "powerHpTo": 110,
               "powerKwFrom": 81,
               "powerKwTo": 81,
               "typeName": "1.2 PureTech 110",
               "typeNumber": 130752,
               "valves": 4,
               "yearOfConstrFrom": 201809,
               "rmiTypeId": 143581
            },
            "vehicleDocId": "DR130752"
         }
      ]
   },
   "status": 200
}