{
   "data": {
      "array": [
         {
            "carId": 17850,
            "vehicleDetails": {
               "carId": 17850,
               "ccmTech": 2230,
               "constructionType": "A trois volumes",
               "cylinder": 4,
               "cylinderCapacityCcm": 2230,
               "cylinderCapacityLiter": 220,
               "fuelType": "Essence",
               "fuelTypeProcess": "Injection dans le collecteur d'admission/Carburateur",
               "impulsionType": "Traction avant",
               "manuId": 88,
               "manuName": "PEUGEOT",
               "modId": 5099,
               "modelName": "407 (6D_)",
               "motorType": "Essence",
               "powerHpFrom": 158,
               "powerHpTo": 158,
               "powerKwFrom": 116,
               "powerKwTo": 116,
               "typeName": "2.2 (6D3FZE, 6D3FZH)",
               "typeNumber": 17850,
               "valves": 4,
               "yearOfConstrFrom": 200403,
               "yearOfConstrTo": 200610,
               "rmiTypeId": 13882
            },
            "vehicleDocId": "DR17850"
         }
      ]
   },
   "status": 200
}