{
   "data": {
      "array": [
         {
            "carId": 18389,
            "vehicleDetails": {
               "carId": 18389,
               "ccmTech": 1390,
               "constructionType": "A trois volumes",
               "cylinder": 4,
               "cylinderCapacityCcm": 1390,
               "cylinderCapacityLiter": 140,
               "fuelType": "Essence",
               "fuelTypeProcess": "Injection dans le collecteur d'admission/Carburateur",
               "impulsionType": "Traction avant",
               "manuId": 139,
               "manuName": "DACIA",
               "modId": 5380,
               "modelName": "LOGAN (LS_)",
               "motorType": "Essence",
               "powerHpFrom": 75,
               "powerHpTo": 75,
               "powerKwFrom": 55,
               "powerKwTo": 55,
               "typeName": "1.4 (LSOA, LSOC, LSOE, LSOG)",
               "typeNumber": 18389,
               "valves": 2,
               "yearOfConstrFrom": 200409,
               "rmiTypeId": 30892
            },
            "vehicleDocId": "DR18389"
         }
      ]
   },
   "status": 200
}