{
   "data": {
      "array": [
         {
            "carId": 18847,
            "vehicleDetails": {
               "carId": 18847,
               "ccmTech": 1986,
               "constructionType": "A trois volumes",
               "cylinder": 4,
               "cylinderCapacityCcm": 1986,
               "cylinderCapacityLiter": 200,
               "fuelType": "Essence",
               "fuelTypeProcess": "Injection dans le collecteur d'admission/Carburateur",
               "impulsionType": "Propulsion",
               "manuId": 120,
               "manuName": "VOLVO",
               "modId": 553,
               "modelName": "740 (744)",
               "motorType": "Essence",
               "powerHpFrom": 150,
               "powerHpTo": 150,
               "powerKwFrom": 110,
               "powerKwTo": 110,
               "typeName": "2.0",
               "typeNumber": 18847,
               "valves": 2,
               "yearOfConstrFrom": 198312,
               "yearOfConstrTo": 198407,
               "rmiTypeId": 38014
            },
            "vehicleDocId": "DR18847"
         }
      ]
   },
   "status": 200
}