{
   "data": {
      "array": [
         {
            "carId": 2911,
            "vehicleDetails": {
               "brakeSystem": "hydraulique",
               "carId": 2911,
               "ccmTech": 1896,
               "constructionType": "3/5 portes",
               "cylinder": 4,
               "cylinderCapacityCcm": 1896,
               "cylinderCapacityLiter": 190,
               "fuelType": "Diesel",
               "fuelTypeProcess": "Moteur à injection indirecte",
               "impulsionType": "Traction avant",
               "manuId": 104,
               "manuName": "SEAT",
               "modId": 569,
               "modelName": "IBIZA II (6K1)",
               "motorType": "Diesel",
               "powerHpFrom": 75,
               "powerHpTo": 75,
               "powerKwFrom": 55,
               "powerKwTo": 55,
               "typeName": "1.9 TD",
               "typeNumber": 2911,
               "valves": 2,
               "yearOfConstrFrom": 199303,
               "yearOfConstrTo": 199608,
               "rmiTypeId": 2661
            },
            "vehicleDocId": "DR2911"
         }
      ]
   },
   "status": 200
}