{
   "data": {
      "array": [
         {
            "carId": 50431,
            "vehicleDetails": {
               "carId": 50431,
               "ccmTech": 4969,
               "constructionType": "A trois volumes",
               "cylinder": 8,
               "cylinderCapacityCcm": 4969,
               "cylinderCapacityLiter": 500,
               "fuelType": "Essence/électrique",
               "fuelTypeProcess": "Injection dans le collecteur d'admission, Injection directe",
               "impulsionType": "Traction intégrale",
               "manuId": 842,
               "manuName": "LEXUS",
               "modId": 6742,
               "modelName": "LS (_F4_)",
               "motorType": "Hybride non rechargeable",
               "powerHpFrom": 445,
               "powerHpTo": 445,
               "powerKwFrom": 327,
               "powerKwTo": 327,
               "typeName": "600h AWD (UVF45, UVF46)",
               "typeNumber": 50431,
               "valves": 4,
               "yearOfConstrFrom": 200709,
               "rmiTypeId": 106072
            },
            "vehicleDocId": "DR50431"
         }
      ]
   },
   "status": 200
}