{
   "data": {
      "array": [
         {
            "carId": 57243,
            "vehicleDetails": {
               "carId": 57243,
               "ccmTech": 3498,
               "constructionType": "Break",
               "cylinder": 6,
               "cylinderCapacityCcm": 3498,
               "cylinderCapacityLiter": 350,
               "fuelType": "Essence",
               "fuelTypeProcess": "Injection directe",
               "impulsionType": "Propulsion",
               "manuId": 74,
               "manuName": "MERCEDES-BENZ",
               "modId": 10848,
               "modelName": "CLS Shooting Brake (X218)",
               "motorType": "Essence",
               "powerHpFrom": 306,
               "powerHpTo": 306,
               "powerKwFrom": 225,
               "powerKwTo": 225,
               "typeName": "CLS 350 (218.959)",
               "typeNumber": 57243,
               "valves": 4,
               "yearOfConstrFrom": 201210,
               "yearOfConstrTo": 201408,
               "rmiTypeId": 74054
            },
            "vehicleDocId": "DR57243"
         }
      ]
   },
   "status": 200
}