{
   "data": {
      "array": [
         {
            "articleId": 1253837876,
            "articleLinkId": 1253837881,
            "articleNo": "200316",
            "articleStateId": 0,
            "brandName": "VALEO",
            "brandNo": 21,
            "genericArticleId": 4,
            "genericArticleName": "Alternateur",
            "sortNo": 1253837881
         },
         {
            "articleId": 13100721,
            "articleLinkId": 182205677,
            "articleNo": "440489",
            "articleStateId": 0,
            "brandName": "VALEO",
            "brandNo": 21,
            "genericArticleId": 4,
            "genericArticleName": "Alternateur",
            "sortNo": 182205677
         },
         {
            "articleId": 13100824,
            "articleLinkId": 470588109,
            "articleNo": "440494",
            "articleStateId": 1,
            "brandName": "VALEO",
            "brandNo": 21,
            "genericArticleId": 4,
            "genericArticleName": "Alternateur",
            "sortNo": 470588109
         },
         {
            "articleId": 410391978,
            "articleLinkId": 435404290,
            "articleNo": "440893",
            "articleStateId": 8,
            "brandName": "VALEO",
            "brandNo": 21,
            "genericArticleId": 4,
            "genericArticleName": "Alternateur",
            "sortNo": 435404290
         },
         {
            "articleId": 582601197,
            "articleLinkId": 582601202,
            "articleNo": "443107",
            "articleStateId": 1,
            "brandName": "VALEO",
            "brandNo": 21,
            "genericArticleId": 4,
            "genericArticleName": "Alternateur",
            "sortNo": 582601202
         },
         {
            "articleId": 410398101,
            "articleLinkId": 470590447,
            "articleNo": "443122",
            "articleStateId": 1,
            "brandName": "VALEO",
            "brandNo": 21,
            "genericArticleId": 4,
            "genericArticleName": "Alternateur",
            "sortNo": 470590447
         }
      ]
   },
   "status": 200
}