{
   "data": {
      "array": [
         {
            "articleId": 13151183,
            "articleLinkId": 236040243,
            "articleNo": "506655",
            "articleStateId": 1,
            "brandName": "VALEO",
            "brandNo": 21,
            "genericArticleId": 1260,
            "genericArticleName": "Pompe à eau, refroidissement du moteur",
            "sortNo": 236040243
         },
         {
            "articleId": 144814712,
            "articleLinkId": 435630125,
            "articleNo": "614514",
            "articleStateId": 1,
            "brandName": "VALEO",
            "brandNo": 21,
            "genericArticleId": 3096,
            "genericArticleName": "Pompe à eau + kit de courroie de distribution",
            "sortNo": 435630125
         },
         {
            "articleId": 144816047,
            "articleLinkId": 378630626,
            "articleNo": "614535",
            "articleStateId": 1,
            "brandName": "VALEO",
            "brandNo": 21,
            "genericArticleId": 3096,
            "genericArticleName": "Pompe à eau + kit de courroie de distribution",
            "sortNo": 378630626
         },
         {
            "articleId": 378632025,
            "articleLinkId": 378632029,
            "articleNo": "614573",
            "articleStateId": 1,
            "brandName": "VALEO",
            "brandNo": 21,
            "genericArticleId": 3096,
            "genericArticleName": "Pompe à eau + kit de courroie de distribution",
            "sortNo": 378632029
         }
      ]
   },
   "status": 200
}