{
   "data": {
      "array": [
         {
            "articleAttributes": {
               "array": [
                  {
                     "attrBlockNo": 0,
                     "attrId": 468,
                     "attrIsConditional": false,
                     "attrIsInterval": false,
                     "attrIsLinked": false,
                     "attrName": "Matériel",
                     "attrType": "K",
                     "attrValue": "Polyester",
                     "attrValueId": 44339
                  },
                  {
                     "attrBlockNo": 0,
                     "attrId": 468,
                     "attrIsConditional": false,
                     "attrIsInterval": false,
                     "attrIsLinked": false,
                     "attrName": "Matériel",
                     "attrType": "K",
                     "attrValue": "EPDM (éthylène-propylène-diène-caoutchouc)",
                     "attrValueId": 3165
                  },
                  {
                     "attrBlockNo": 0,
                     "attrId": 436,
                     "attrIsConditional": false,
                     "attrIsInterval": false,
                     "attrIsLinked": false,
                     "attrName": "Couleur",
                     "attrType": "K",
                     "attrValue": "noir",
                     "attrValueId": 25314
                  },
                  {
                     "attrBlockNo": 0,
                     "attrId": 490,
                     "attrIsConditional": false,
                     "attrIsInterval": false,
                     "attrIsLinked": false,
                     "attrName": "Nombre de stries",
                     "attrShortName": "Nombre de gorges",
                     "attrType": "N",
                     "attrValue": "4",
                     "attrValueId": 47559
                  },
                  {
                     "attrBlockNo": 0,
                     "attrId": 206,
                     "attrIsConditional": false,
                     "attrIsInterval": false,
                     "attrIsLinked": false,
                     "attrName": "Largeur [mm]",
                     "attrShortName": "Largeur",
                     "attrType": "N",
                     "attrUnit": "mm",
                     "attrValue": "14,2",
                     "attrValueId": 51054
                  },
                  {
                     "attrBlockNo": 0,
                     "attrId": 203,
                     "attrIsConditional": false,
                     "attrIsInterval": false,
                     "attrIsLinked": false,
                     "attrName": "Longueur [mm]",
                     "attrShortName": "Longueur",
                     "attrType": "N",
                     "attrUnit": "mm",
                     "attrValue": "780",
                     "attrValueId": 7198
                  }
               ]
            },
            "articleDocuments": {
               "array": [
                  {
                     "docFileName": "4PK-1_FRO_R-1.JPG",
                     "docFileTypeName": "Fichier image JPEG",
                     "docId": "845520150097379",
                     "docTypeId": 5,
                     "docTypeName": "Illustration"
                  },
                  {
                     "docFileName": "4PK-2_ANG_R-1.JPG",
                     "docFileTypeName": "Fichier image JPEG",
                     "docId": "845520150097380",
                     "docTypeId": 5,
                     "docTypeName": "Illustration"
                  },
                  {
                     "docFileTypeName": "URL",
                     "docId": "1126995126807253",
                     "docTypeId": 14,
                     "docTypeName": "Mode d'emploi"
                  },
                  {
                     "docFileTypeName": "URL",
                     "docId": "1126995126807254",
                     "docTypeId": 14,
                     "docTypeName": "Mode d'emploi"
                  }
               ]
            },
            "articleInfo": "",
            "articlePrices": "",
            "articleThumbnails": {
               "array": [
                  {
                     "thumbDocId": "845520150097379",
                     "thumbFileName": "0033\\4PK-1_FRO_R-1.JPG",
                     "thumbTypeId": 5
                  },
                  {
                     "thumbDocId": "845520150097380",
                     "thumbFileName": "0033\\4PK-2_ANG_R-1.JPG",
                     "thumbTypeId": 5
                  }
               ]
            },
            "directArticle": {
               "articleAddName": "Micro-V®",
               "articleId": 17063671,
               "articleName": "Courroie trapézoïdale à nervures",
               "articleNo": "4PK780",
               "articleState": 1,
               "articleStateName": "Normal",
               "brandName": "GATES",
               "brandNo": 33,
               "flagAccessories": false,
               "flagCertificationCompulsory": false,
               "flagRemanufacturedPart": false,
               "flagSuitedforSelfService": false,
               "genericArticleId": 305,
               "hasAppendage": false,
               "hasAxleLink": false,
               "hasCsGraphics": false,
               "hasDocuments": true,
               "hasLessDiscount": false,
               "hasMarkLink": false,
               "hasMotorLink": false,
               "hasOEN": true,
               "hasPartList": false,
               "hasPrices": false,
               "hasSecurityInfo": false,
               "hasUsage": true,
               "hasVehicleLink": true,
               "packingUnit": 1
            },
            "eanNumber": {
               "array": [
                  {
                     "eanNumber": "5414465354809"
                  }
               ]
            },
            "mainArticle": {
               "array": [
                  {
                     "articleAddName": "Micro-V® Kit",
                     "articleId": 17174478,
                     "articleName": "Jeu de courroies trapézoïdales à nervures",
                     "articleNumber": "K014PK545"
                  },
                  {
                     "articleAddName": "Micro-V® Kit",
                     "articleId": 17174514,
                     "articleName": "Jeu de courroies trapézoïdales à nervures",
                     "articleNumber": "K014PK780"
                  },
                  {
                     "articleAddName": "Micro-V® Kit",
                     "articleId": 17195758,
                     "articleName": "Jeu de courroies trapézoïdales à nervures",
                     "articleNumber": "K024PK550"
                  },
                  {
                     "articleAddName": "Micro-V® Kit",
                     "articleId": 17195806,
                     "articleName": "Jeu de courroies trapézoïdales à nervures",
                     "articleNumber": "K024PK780"
                  },
                  {
                     "articleAddName": "Micro-V® Kit",
                     "articleId": 17206793,
                     "articleName": "Jeu de courroies trapézoïdales à nervures",
                     "articleNumber": "K034PK780"
                  },
                  {
                     "articleAddName": "Micro-V® Kit",
                     "articleId": 17217394,
                     "articleName": "Jeu de courroies trapézoïdales à nervures",
                     "articleNumber": "K064PK780"
                  }
               ]
            },
            "normalAustauschPrice": "",
            "oenNumbers": {
               "array": [
                  {
                     "blockNumber": 1,
                     "brandName": "BMW",
                     "oeNumber": "11282243732",
                     "sortNumber": 1
                  },
                  {
                     "blockNumber": 2,
                     "brandName": "BMW",
                     "oeNumber": "64552243732",
                     "sortNumber": 1
                  },
                  {
                     "blockNumber": 3,
                     "brandName": "BMW",
                     "oeNumber": "64552245451",
                     "sortNumber": 1
                  },
                  {
                     "blockNumber": 4,
                     "brandName": "BMW",
                     "oeNumber": "64552246732",
                     "sortNumber": 1
                  },
                  {
                     "blockNumber": 1,
                     "brandName": "DAIHATSU",
                     "oeNumber": "90048-31003",
                     "sortNumber": 1
                  },
                  {
                     "blockNumber": 2,
                     "brandName": "DAIHATSU",
                     "oeNumber": "90048-31003-000",
                     "sortNumber": 1
                  },
                  {
                     "blockNumber": 3,
                     "brandName": "DAIHATSU",
                     "oeNumber": "90048-31017",
                     "sortNumber": 1
                  },
                  {
                     "blockNumber": 4,
                     "brandName": "DAIHATSU",
                     "oeNumber": "90048-31017-000",
                     "sortNumber": 1
                  },
                  {
                     "blockNumber": 5,
                     "brandName": "DAIHATSU",
                     "oeNumber": "90048-31019",
                     "sortNumber": 1
                  },
                  {
                     "blockNumber": 6,
                     "brandName": "DAIHATSU",
                     "oeNumber": "90048-31019-000",
                     "sortNumber": 1
                  },
                  {
                     "blockNumber": 1,
                     "brandName": "DODGE",
                     "oeNumber": "MD163032",
                     "sortNumber": 1
                  },
                  {
                     "blockNumber": 1,
                     "brandName": "FIAT",
                     "oeNumber": "46443510",
                     "sortNumber": 1
                  },
                  {
                     "blockNumber": 2,
                     "brandName": "FIAT",
                     "oeNumber": "46557131",
                     "sortNumber": 1
                  },
                  {
                     "blockNumber": 3,
                     "brandName": "FIAT",
                     "oeNumber": "71739925",
                     "sortNumber": 1
                  },
                  {
                     "blockNumber": 1,
                     "brandName": "HONDA",
                     "oeNumber": "31110-P01-003",
                     "sortNumber": 1
                  },
                  {
                     "blockNumber": 2,
                     "brandName": "HONDA",
                     "oeNumber": "31110-P01-004",
                     "sortNumber": 1
                  },
                  {
                     "blockNumber": 3,
                     "brandName": "HONDA",
                     "oeNumber": "31110-P2J-004",
                     "sortNumber": 1
                  },
                  {
                     "blockNumber": 4,
                     "brandName": "HONDA",
                     "oeNumber": "31110-P30-901",
                     "sortNumber": 1
                  },
                  {
                     "blockNumber": 5,
                     "brandName": "HONDA",
                     "oeNumber": "31110-P72-902",
                     "sortNumber": 1
                  },
                  {
                     "blockNumber": 6,
                     "brandName": "HONDA",
                     "oeNumber": "31110-PO1-003",
                     "sortNumber": 1
                  },
                  {
                     "blockNumber": 7,
                     "brandName": "HONDA",
                     "oeNumber": "31110-PO1-0032",
                     "sortNumber": 1
                  },
                  {
                     "blockNumber": 8,
                     "brandName": "HONDA",
                     "oeNumber": "31110-PO1-004",
                     "sortNumber": 1
                  },
                  {
                     "blockNumber": 1,
                     "brandName": "ISUZU",
                     "oeNumber": "31110-P01-003",
                     "sortNumber": 1
                  },
                  {
                     "blockNumber": 2,
                     "brandName": "ISUZU",
                     "oeNumber": "31110-P01-004",
                     "sortNumber": 1
                  },
                  {
                     "blockNumber": 1,
                     "brandName": "MAZDA",
                     "oeNumber": "N3H115908",
                     "sortNumber": 1
                  },
                  {
                     "blockNumber": 2,
                     "brandName": "MAZDA",
                     "oeNumber": "N3H115908A",
                     "sortNumber": 1
                  },
                  {
                     "blockNumber": 3,
                     "brandName": "MAZDA",
                     "oeNumber": "N3R1-15-908",
                     "sortNumber": 1
                  },
                  {
                     "blockNumber": 1,
                     "brandName": "MITSUBISHI",
                     "oeNumber": "1340A066",
                     "sortNumber": 1
                  },
                  {
                     "blockNumber": 2,
                     "brandName": "MITSUBISHI",
                     "oeNumber": "31110P2T003",
                     "sortNumber": 1
                  },
                  {
                     "blockNumber": 3,
                     "brandName": "MITSUBISHI",
                     "oeNumber": "4451A106",
                     "sortNumber": 1
                  },
                  {
                     "blockNumber": 4,
                     "brandName": "MITSUBISHI",
                     "oeNumber": "MD163032",
                     "sortNumber": 1
                  },
                  {
                     "blockNumber": 5,
                     "brandName": "MITSUBISHI",
                     "oeNumber": "MD171373",
                     "sortNumber": 1
                  },
                  {
                     "blockNumber": 6,
                     "brandName": "MITSUBISHI",
                     "oeNumber": "MD334464",
                     "sortNumber": 1
                  },
                  {
                     "blockNumber": 7,
                     "brandName": "MITSUBISHI",
                     "oeNumber": "MD343575",
                     "sortNumber": 1
                  },
                  {
                     "blockNumber": 8,
                     "brandName": "MITSUBISHI",
                     "oeNumber": "MN187176",
                     "sortNumber": 1
                  },
                  {
                     "blockNumber": 1,
                     "brandName": "NISSAN",
                     "oeNumber": "11950-8J100",
                     "sortNumber": 1
                  },
                  {
                     "blockNumber": 1,
                     "brandName": "OPEL",
                     "oeNumber": "1854722",
                     "sortNumber": 1
                  },
                  {
                     "blockNumber": 2,
                     "brandName": "OPEL",
                     "oeNumber": "1854725",
                     "sortNumber": 1
                  },
                  {
                     "blockNumber": 3,
                     "brandName": "OPEL",
                     "oeNumber": "64552245451",
                     "sortNumber": 1
                  },
                  {
                     "blockNumber": 4,
                     "brandName": "OPEL",
                     "oeNumber": "90509751",
                     "sortNumber": 1
                  },
                  {
                     "blockNumber": 5,
                     "brandName": "OPEL",
                     "oeNumber": "90512538",
                     "sortNumber": 1
                  },
                  {
                     "blockNumber": 1,
                     "brandName": "RENAULT",
                     "oeNumber": "7700734112",
                     "sortNumber": 1
                  },
                  {
                     "blockNumber": 2,
                     "brandName": "RENAULT",
                     "oeNumber": "R7700734112",
                     "sortNumber": 1
                  },
                  {
                     "blockNumber": 3,
                     "brandName": "RENAULT",
                     "oeNumber": "T0734112",
                     "sortNumber": 1
                  },
                  {
                     "blockNumber": 1,
                     "brandName": "TOYOTA",
                     "oeNumber": "9936430780",
                     "sortNumber": 1
                  },
                  {
                     "blockNumber": 1,
                     "brandName": "VAUXHALL",
                     "oeNumber": "1854722",
                     "sortNumber": 1
                  },
                  {
                     "blockNumber": 2,
                     "brandName": "VAUXHALL",
                     "oeNumber": "1854725",
                     "sortNumber": 1
                  },
                  {
                     "blockNumber": 3,
                     "brandName": "VAUXHALL",
                     "oeNumber": "64552245451",
                     "sortNumber": 1
                  },
                  {
                     "blockNumber": 4,
                     "brandName": "VAUXHALL",
                     "oeNumber": "90509751",
                     "sortNumber": 1
                  },
                  {
                     "blockNumber": 5,
                     "brandName": "VAUXHALL",
                     "oeNumber": "90512538",
                     "sortNumber": 1
                  },
                  {
                     "blockNumber": 1,
                     "brandName": "VOLVO",
                     "oeNumber": "30873534",
                     "sortNumber": 1
                  },
                  {
                     "blockNumber": 2,
                     "brandName": "VOLVO",
                     "oeNumber": "MD343575",
                     "sortNumber": 1
                  },
                  {
                     "blockNumber": 1,
                     "brandName": "HYUNDAI",
                     "oeNumber": "2521202550",
                     "sortNumber": 1
                  },
                  {
                     "blockNumber": 2,
                     "brandName": "HYUNDAI",
                     "oeNumber": "2521202551",
                     "sortNumber": 1
                  },
                  {
                     "blockNumber": 3,
                     "brandName": "HYUNDAI",
                     "oeNumber": "2521202552",
                     "sortNumber": 1
                  },
                  {
                     "blockNumber": 1,
                     "brandName": "KIA",
                     "oeNumber": "2521202550",
                     "sortNumber": 1
                  },
                  {
                     "blockNumber": 2,
                     "brandName": "KIA",
                     "oeNumber": "2521202551",
                     "sortNumber": 1
                  },
                  {
                     "blockNumber": 3,
                     "brandName": "KIA",
                     "oeNumber": "2521202552",
                     "sortNumber": 1
                  },
                  {
                     "blockNumber": 1,
                     "brandName": "PROTON",
                     "oeNumber": "MD171373",
                     "sortNumber": 1
                  },
                  {
                     "blockNumber": 2,
                     "brandName": "PROTON",
                     "oeNumber": "PW510943",
                     "sortNumber": 1
                  },
                  {
                     "blockNumber": 1,
                     "brandName": "PLYMOUTH",
                     "oeNumber": "MD163032",
                     "sortNumber": 1
                  },
                  {
                     "blockNumber": 1,
                     "brandName": "MARUTI",
                     "oeNumber": "95141M55R30",
                     "sortNumber": 1
                  },
                  {
                     "blockNumber": 2,
                     "brandName": "MARUTI",
                     "oeNumber": "95141M65L10",
                     "sortNumber": 1
                  }
               ]
            },
            "replacedByNumber": "",
            "replacedNumber": "",
            "usageNumbers": {
               "array": [
                  {
                     "usageNumber": "48347"
                  },
                  {
                     "usageNumber": "4PK778"
                  },
                  {
                     "usageNumber": "4PK779"
                  },
                  {
                     "usageNumber": "4PK781"
                  },
                  {
                     "usageNumber": "4PK783"
                  },
                  {
                     "usageNumber": "8653-10062"
                  }
               ]
            }
         }
      ]
   },
   "status": 200
}