{
   "data": {
      "array": [
         {
            "articleAttributes": {
               "array": [
                  {
                     "attrBlockNo": 0,
                     "attrId": 100,
                     "attrIsConditional": false,
                     "attrIsInterval": false,
                     "attrIsLinked": false,
                     "attrName": "Côté d'assemblage",
                     "attrShortName": "Endroit d'assemblage",
                     "attrType": "K",
                     "attrValue": "Essieu avant",
                     "attrValueId": 29988
                  },
                  {
                     "attrBlockNo": 0,
                     "attrId": 649,
                     "attrIsConditional": false,
                     "attrIsInterval": false,
                     "attrIsLinked": false,
                     "attrName": "Système de freinage",
                     "attrShortName": "Système de freinage",
                     "attrType": "A",
                     "attrValue": "AKEBONO",
                     "attrValueId": 64377
                  },
                  {
                     "attrBlockNo": 0,
                     "attrId": 836,
                     "attrIsConditional": false,
                     "attrIsInterval": false,
                     "attrIsLinked": false,
                     "attrName": "Article complémentaire / Info complémentaire 2",
                     "attrType": "K",
                     "attrValue": "sans kit de vis de fixation",
                     "attrValueId": 46231
                  },
                  {
                     "attrBlockNo": 0,
                     "attrId": 206,
                     "attrIsConditional": false,
                     "attrIsInterval": false,
                     "attrIsLinked": false,
                     "attrName": "Largeur [mm]",
                     "attrShortName": "Largeur",
                     "attrType": "N",
                     "attrUnit": "mm",
                     "attrValue": "142",
                     "attrValueId": 64118
                  },
                  {
                     "attrBlockNo": 0,
                     "attrId": 209,
                     "attrIsConditional": false,
                     "attrIsInterval": false,
                     "attrIsLinked": false,
                     "attrName": "Hauteur [mm]",
                     "attrShortName": "Hauteur",
                     "attrType": "N",
                     "attrUnit": "mm",
                     "attrValue": "59,8",
                     "attrValueId": 21635
                  },
                  {
                     "attrBlockNo": 0,
                     "attrId": 124,
                     "attrIsConditional": false,
                     "attrIsInterval": false,
                     "attrIsLinked": false,
                     "attrName": "Épaisseur [mm]",
                     "attrShortName": "Épaisseur",
                     "attrType": "N",
                     "attrUnit": "mm",
                     "attrValue": "16,1",
                     "attrValueId": 24883
                  },
                  {
                     "attrBlockNo": 0,
                     "attrId": 1182,
                     "attrIsConditional": false,
                     "attrIsInterval": false,
                     "attrIsLinked": false,
                     "attrName": "numéro WVA",
                     "attrShortName": "numéro WVA",
                     "attrType": "A",
                     "attrValue": "22065",
                     "attrValueId": 24295
                  },
                  {
                     "attrBlockNo": 0,
                     "attrId": 593,
                     "attrIsConditional": false,
                     "attrIsInterval": false,
                     "attrIsLinked": false,
                     "attrName": "Indicateur d'usure",
                     "attrType": "K",
                     "attrValue": "contact de signal d'usure inclu",
                     "attrValueId": 2226
                  },
                  {
                     "attrBlockNo": 0,
                     "attrId": 264,
                     "attrIsConditional": false,
                     "attrIsInterval": false,
                     "attrIsLinked": false,
                     "attrName": "Nombre d'indicateurs d'usure [par essieu]",
                     "attrShortName": "Nombre d'indicateurs d'usure",
                     "attrType": "N",
                     "attrUnit": "par essieu",
                     "attrValue": "1",
                     "attrValueId": 64841
                  },
                  {
                     "attrBlockNo": 0,
                     "attrId": 439,
                     "attrIsConditional": false,
                     "attrIsInterval": false,
                     "attrIsLinked": false,
                     "attrName": "Type de fonctionnement",
                     "attrType": "K",
                     "attrValue": "mécanique",
                     "attrValueId": 60528
                  },
                  {
                     "attrBlockNo": 0,
                     "attrId": 836,
                     "attrIsConditional": false,
                     "attrIsInterval": false,
                     "attrIsLinked": false,
                     "attrName": "Article complémentaire / Info complémentaire 2",
                     "attrType": "K",
                     "attrValue": "avec tôle anti-bruit",
                     "attrValueId": 1865
                  },
                  {
                     "attrBlockNo": 0,
                     "attrId": 190,
                     "attrIsConditional": false,
                     "attrIsInterval": false,
                     "attrIsLinked": false,
                     "attrName": "Marque de conformité",
                     "attrShortName": "Marque de conformité",
                     "attrType": "A",
                     "attrValue": "ECE-R90",
                     "attrValueId": 19
                  },
                  {
                     "attrBlockNo": 0,
                     "attrId": 212,
                     "attrIsConditional": false,
                     "attrIsInterval": false,
                     "attrIsLinked": false,
                     "attrName": "Poids [kg]",
                     "attrShortName": "Poids",
                     "attrType": "N",
                     "attrUnit": "kg",
                     "attrValue": "1,81",
                     "attrValueId": 2245
                  }
               ]
            },
            "articleDocuments": {
               "array": [
                  {
                     "docFileName": "BRAKE_PAD_601733_01.JPG",
                     "docFileTypeName": "Fichier image JPEG",
                     "docId": "845520148950885",
                     "docTypeId": 3,
                     "docTypeName": "Dessin technique"
                  }
               ]
            },
            "articleInfo": {
               "array": [
                  {
                     "infoId": 38841,
                     "infoText": "1923-2023: 100 ans de freinage",
                     "infoType": 2,
                     "infoTypeName": "Informations générales"
                  }
               ]
            },
            "articlePrices": "",
            "articleThumbnails": {
               "array": [
                  {
                     "thumbDocId": "845520148950885",
                     "thumbFileName": "0021\\BRAKE_PAD_601733_01.JPG",
                     "thumbTypeId": 3
                  }
               ]
            },
            "directArticle": {
               "articleId": 868963533,
               "articleName": "Kit de plaquettes de frein, frein à disque",
               "articleNo": "601733",
               "articleState": 1,
               "articleStateName": "Normal",
               "brandName": "VALEO",
               "brandNo": 21,
               "flagAccessories": false,
               "flagCertificationCompulsory": false,
               "flagRemanufacturedPart": false,
               "flagSuitedforSelfService": false,
               "genericArticleId": 402,
               "hasAppendage": false,
               "hasAxleLink": false,
               "hasCsGraphics": false,
               "hasDocuments": true,
               "hasLessDiscount": false,
               "hasMarkLink": false,
               "hasMotorLink": false,
               "hasOEN": true,
               "hasPartList": false,
               "hasPrices": false,
               "hasSecurityInfo": false,
               "hasUsage": false,
               "hasVehicleLink": true,
               "packingUnit": 1
            },
            "eanNumber": {
               "array": [
                  {
                     "eanNumber": "3276426017336"
                  }
               ]
            },
            "mainArticle": "",
            "normalAustauschPrice": "",
            "oenNumbers": {
               "array": [
                  {
                     "blockNumber": 1,
                     "brandName": "NISSAN",
                     "oeNumber": "D1060-4CA0A",
                     "sortNumber": 1
                  },
                  {
                     "blockNumber": 2,
                     "brandName": "NISSAN",
                     "oeNumber": "D10604CA0A",
                     "sortNumber": 1
                  },
                  {
                     "blockNumber": 1,
                     "brandName": "RENAULT",
                     "oeNumber": "410601596R",
                     "sortNumber": 1
                  }
               ]
            },
            "replacedByNumber": "",
            "replacedNumber": "",
            "usageNumbers": ""
         }
      ]
   },
   "status": 200
}